isleservice_objects/__init__.py
isleservice_objects/_version.py
isleservice_objects/errors.py
isleservice_objects/fields.py
isleservice_objects/models.py
isleservice_objects/schemas.py
isleservice_objects-0.2.1.dist-info/LICENSE
isleservice_objects-0.2.1.dist-info/METADATA
isleservice_objects-0.2.1.dist-info/WHEEL
isleservice_objects-0.2.1.dist-info/top_level.txt
isleservice_objects-0.2.1.dist-info/RECORD
